lab4/clock divider by 3/rtl/clock_div_3.v
module clk_div_3(input clk,reset,
		 output reg [1:0] pos_count, neg_count, 
		 output clk_out);
 
	always @(posedge clk) begin
		if (reset)
			pos_count <=0;
		else if (pos_count ==2) 
			pos_count <= 0;
		else 
			pos_count<= pos_count +1;
	end
 
	always @(negedge clk) begin
		if (reset)
			neg_count <=0;
		else  if (neg_count == 2) 
			neg_count <= 0;
		else 
			neg_count<= neg_count +1;
	end
 
assign clk_out = ((pos_count == 2) | (neg_count == 2));
endmodule

lab4/clock divider by 3/tb/tb_clock_div_3.v
`timescale 1ns/100ps
module clkdiv3_tb;
  reg clk,reset;
  wire [1:0] pos_count,neg_count;
  wire clk_out;
 
	clk_div_3 DUT(.clk(clk),.reset(reset),.pos_count(pos_count),.neg_count(neg_count),.clk_out(clk_out));

	initial begin
            	clk= 1'b0;
		reset = 1'b0;
	end

     	always begin
        	#5  clk=~clk; 
	end

        initial
            begin
               #25 reset=1'b1;
               #10 reset=1'b0;
	       #150 reset = 1'b1;
	       #20 reset = 1'b0;
               #500 $finish;
         end
 
        initial begin
               $monitor("clk=%b,reset=%b,pos_count=%2b,neg_count=%2b,clk_out=%b",clk,reset,pos_count,neg_count,clk_out);
	end
 
        initial begin
              $dumpfile("clkdiv3_tb.vcd");
              $dumpvars(0,clkdiv3_tb);
        end

    endmodule

lab4/clock divider by 3/sim/clkdiv3_tb.vcd
$date
	Sat Aug 28 19:42:21 2021
$end
$version
	ModelSim Version 2020.1
$end
$timescale
	100ps
$end

$scope module clkdiv3_tb $end
$var reg 1 ! clk $end
$var reg 1 " reset $end
$var wire 1 # pos_count [1] $end
$var wire 1 $ pos_count [0] $end
$var wire 1 % neg_count [1] $end
$var wire 1 & neg_count [0] $end
$var wire 1 ' clk_out $end

$scope module DUT $end
$var wire 1 ( clk $end
$var wire 1 ) reset $end
$var reg 2 * pos_count [1:0] $end
$var reg 2 + neg_count [1:0] $end
$var wire 1 ' clk_out $end
$upscope $end
$upscope $end
$enddefinitions $end
#0
$dumpvars
0!
0"
bx *
bx +
x$
x#
x&
x%
x'
0)
0(
$end
#50
1!
1(
#100
0!
0(
#150
1!
1(
#200
0!
0(
#250
1"
1!
1)
1(
b0 *
0$
0#
#300
0!
0(
b0 +
0'
0&
0%
#350
0"
1!
0)
1(
b1 *
1$
#400
0!
0(
b1 +
1&
#450
1!
1(
b10 *
1'
0$
1#
#500
0!
0(
b10 +
0&
1%
#550
1!
1(
b0 *
0#
#600
0!
0(
b0 +
0'
0%
#650
1!
1(
b1 *
1$
#700
0!
0(
b1 +
1&
#750
1!
1(
b10 *
1'
0$
1#
#800
0!
0(
b10 +
0&
1%
#850
1!
1(
b0 *
0#
#900
0!
0(
b0 +
0'
0%
#950
1!
1(
b1 *
1$
#1000
0!
0(
b1 +
1&
#1050
1!
1(
b10 *
1'
0$
1#
#1100
0!
0(
b10 +
0&
1%
#1150
1!
1(
b0 *
0#
#1200
0!
0(
b0 +
0'
0%
#1250
1!
1(
b1 *
1$
#1300
0!
0(
b1 +
1&
#1350
1!
1(
b10 *
1'
0$
1#
#1400
0!
0(
b10 +
0&
1%
#1450
1!
1(
b0 *
0#
#1500
0!
0(
b0 +
0'
0%
#1550
1!
1(
b1 *
1$
#1600
0!
0(
b1 +
1&
#1650
1!
1(
b10 *
1'
0$
1#
#1700
0!
0(
b10 +
0&
1%
#1750
1!
1(
b0 *
0#
#1800
0!
0(
b0 +
0'
0%
#1850
1"
1!
1)
1(
#1900
0!
0(
#1950
1!
1(
#2000
0!
0(
#2050
0"
1!
0)
1(
b1 *
1$
#2100
0!
0(
b1 +
1&
#2150
1!
1(
b10 *
1'
0$
1#
#2200
0!
0(
b10 +
0&
1%
#2250
1!
1(
b0 *
0#
#2300
0!
0(
b0 +
0'
0%
#2350
1!
1(
b1 *
1$
#2400
0!
0(
b1 +
1&
#2450
1!
1(
b10 *
1'
0$
1#
#2500
0!
0(
b10 +
0&
1%
#2550
1!
1(
b0 *
0#
#2600
0!
0(
b0 +
0'
0%
#2650
1!
1(
b1 *
1$
#2700
0!
0(
b1 +
1&
#2750
1!
1(
b10 *
1'
0$
1#
#2800
0!
0(
b10 +
0&
1%
#2850
1!
1(
b0 *
0#
#2900
0!
0(
b0 +
0'
0%
#2950
1!
1(
b1 *
1$
#3000
0!
0(
b1 +
1&
#3050
1!
1(
b10 *
1'
0$
1#
#3100
0!
0(
b10 +
0&
1%
#3150
1!
1(
b0 *
0#
#3200
0!
0(
b0 +
0'
0%
#3250
1!
1(
b1 *
1$
#3300
0!
0(
b1 +
1&
#3350
1!
1(
b10 *
1'
0$
1#
#3400
0!
0(
b10 +
0&
1%
#3450
1!
1(
b0 *
0#
#3500
0!
0(
b0 +
0'
0%
#3550
1!
1(
b1 *
1$
#3600
0!
0(
b1 +
1&
#3650
1!
1(
b10 *
1'
0$
1#
#3700
0!
0(
b10 +
0&
1%
#3750
1!
1(
b0 *
0#
#3800
0!
0(
b0 +
0'
0%
#3850
1!
1(
b1 *
1$
#3900
0!
0(
b1 +
1&
#3950
1!
1(
b10 *
1'
0$
1#
#4000
0!
0(
b10 +
0&
1%
#4050
1!
1(
b0 *
0#
#4100
0!
0(
b0 +
0'
0%
#4150
1!
1(
b1 *
1$
#4200
0!
0(
b1 +
1&
#4250
1!
1(
b10 *
1'
0$
1#
#4300
0!
0(
b10 +
0&
1%
#4350
1!
1(
b0 *
0#
#4400
0!
0(
b0 +
0'
0%
#4450
1!
1(
b1 *
1$
#4500
0!
0(
b1 +
1&
#4550
1!
1(
b10 *
1'
0$
1#
#4600
0!
0(
b10 +
0&
1%
#4650
1!
1(
b0 *
0#
#4700
0!
0(
b0 +
0'
0%
#4750
1!
1(
b1 *
1$
#4800
0!
0(
b1 +
1&
#4850
1!
1(
b10 *
1'
0$
1#
#4900
0!
0(
b10 +
0&
1%
#4950
1!
1(
b0 *
0#
#5000
0!
0(
b0 +
0'
0%
#5050
1!
1(
b1 *
1$
#5100
0!
0(
b1 +
1&
#5150
1!
1(
b10 *
1'
0$
1#
#5200
0!
0(
b10 +
0&
1%
#5250
1!
1(
b0 *
0#
#5300
0!
0(
b0 +
0'
0%
#5350
1!
1(
b1 *
1$
#5400
0!
0(
b1 +
1&
#5450
1!
1(
b10 *
1'
0$
1#
#5500
0!
0(
b10 +
0&
1%
#5550
1!
1(
b0 *
0#
#5600
0!
0(
b0 +
0'
0%
#5650
1!
1(
b1 *
1$
#5700
0!
0(
b1 +
1&
#5750
1!
1(
b10 *
1'
0$
1#
#5800
0!
0(
b10 +
0&
1%
#5850
1!
1(
b0 *
0#
#5900
0!
0(
b0 +
0'
0%
#5950
1!
1(
b1 *
1$
#6000
0!
0(
b1 +
1&
#6050
1!
1(
b10 *
1'
0$
1#
#6100
0!
0(
b10 +
0&
1%
#6150
1!
1(
b0 *
0#
#6200
0!
0(
b0 +
0'
0%
#6250
1!
1(
b1 *
1$
#6300
0!
0(
b1 +
1&
#6350
1!
1(
b10 *
1'
0$
1#
#6400
0!
0(
b10 +
0&
1%
#6450
1!
1(
b0 *
0#
#6500
0!
0(
b0 +
0'
0%
#6550
1!
1(
b1 *
1$
#6600
0!
0(
b1 +
1&
#6650
1!
1(
b10 *
1'
0$
1#
#6700
0!
0(
b10 +
0&
1%
#6750
1!
1(
b0 *
0#
#6800
0!
0(
b0 +
0'
0%
#6850
1!
1(
b1 *
1$
#6900
0!
0(
b1 +
1&
#6950
1!
1(
b10 *
1'
0$
1#
#7000
0!
0(
b10 +
0&
1%
